sphinx_markdown_checkbox/__init__.py
sphinx_markdown_checkbox-0.1.0.data/data/LICENSE
sphinx_markdown_checkbox-0.1.0.dist-info/LICENSE
sphinx_markdown_checkbox-0.1.0.dist-info/METADATA
sphinx_markdown_checkbox-0.1.0.dist-info/WHEEL
sphinx_markdown_checkbox-0.1.0.dist-info/top_level.txt
sphinx_markdown_checkbox-0.1.0.dist-info/RECORD
