Metadata-Version: 2.1
Name: sphinx-markdown-checkbox
Version: 0.1.0
Summary: A Sphinx extension for rendering checkboxes written in markdown
Home-page: UNKNOWN
Author: Russell Zhang
Author-email: zhangtz@163.com
License: UNKNOWN
Project-URL: Bug Reports, https://github.com/RZ16/sphinx-markdown-checkbox/issues
Project-URL: Source, https://github.com/RZ16/sphinx-markdown-checkbox
Keywords: sphinx markdown checkbox tasklist
Platform: UNKNOWN
Classifier: Development Status :: 4 - Beta
Classifier: Intended Audience :: Developers
Classifier: Topic :: Software Development :: Build Tools
Classifier: License :: OSI Approved :: GNU General Public License v3 (GPLv3)
Classifier: Programming Language :: Python :: 3.5
Classifier: Programming Language :: Python :: 3.6
Classifier: Programming Language :: Python :: 3.7
